setup.py
twittermetrics/__init__.py
twittermetrics/alchemyapi.py
twittermetrics/oauth.py
twittermetrics/search.py
twittermetrics/twitter_metrics.py
twittermetrics.egg-info/PKG-INFO
twittermetrics.egg-info/SOURCES.txt
twittermetrics.egg-info/dependency_links.txt
twittermetrics.egg-info/not-zip-safe
twittermetrics.egg-info/requires.txt
twittermetrics.egg-info/top_level.txt