Metadata-Version: 1.0
Name: twittermetrics
Version: 0.1.5
Summary: Twitter search for popular words and sentiment analysis
Home-page: https://github.com/dennokorir/project-mining-twitter.git
Author: Denis Korir
Author-email: dennokorir@gmail.com
License: MIT
Platform: UNKNOWN
